<?xml version="1.0" encoding="utf-8"?>
<XmlTheme xmlns:xsi="http://www.w3.org/2001/XMLSchema-instance" ThemeName="Office2019LightPurple" ThemeVersion="2.0">
  <BuilderRegistrations>
    <XmlStyleBuilderRegistration BuilderType="">
      <BuilderData xsi:type="XmlStyleSheet" xmlns:xsi="http://www.w3.org/2001/XMLSchema-instance">
        <PropertySettingGroups>
          <XmlPropertySettingGroup BasedOn="DefaultFont">
            <PropertySettings>
              <XmlPropertySetting Property="Telerik.WinControls.RadItem.UseDefaultDisabledPaint" Value="False" />
            </PropertySettings>
            <Selectors>
              <XmlTypeSelector ElementType="Telerik.WinControls.RootRadElement" />
            </Selectors>
          </XmlPropertySettingGroup>
          <XmlPropertySettingGroup BasedOn="CollapsedBorder">
            <Selectors>
              <XmlVisualStateSelector VisualState="SplitButton">
                <ChildSelector xsi:type="XmlClassSelector" ElementClass="RadArrowButtonBorder" xmlns:xsi="http://www.w3.org/2001/XMLSchema-instance" />
              </XmlVisualStateSelector>
            </Selectors>
          </XmlPropertySettingGroup>
          <XmlPropertySettingGroup BasedOn="CollapsedBorder">
            <Selectors>
              <XmlVisualStateSelector VisualState="SplitButton">
                <ChildSelector xsi:type="XmlClassSelector" ElementClass="ButtonBorder" xmlns:xsi="http://www.w3.org/2001/XMLSchema-instance" />
              </XmlVisualStateSelector>
            </Selectors>
          </XmlPropertySettingGroup>
          <XmlPropertySettingGroup BasedOn="ButtonBackgroundFill">
            <PropertySettings>
              <XmlPropertySetting Property="Telerik.WinControls.VisualElement.SmoothingMode" Value="None" />
            </PropertySettings>
            <Selectors>
              <XmlVisualStateSelector VisualState="SplitButton">
                <ChildSelector xsi:type="XmlClassSelector" ElementClass="RadArrowButtonFill" xmlns:xsi="http://www.w3.org/2001/XMLSchema-instance" />
              </XmlVisualStateSelector>
            </Selectors>
          </XmlPropertySettingGroup>
          <XmlPropertySettingGroup BasedOn="ButtonBackgroundFill">
            <PropertySettings>
              <XmlPropertySetting Property="Telerik.WinControls.VisualElement.SmoothingMode" Value="None" />
            </PropertySettings>
            <Selectors>
              <XmlVisualStateSelector VisualState="SplitButton">
                <ChildSelector xsi:type="XmlClassSelector" ElementClass="ButtonFill" xmlns:xsi="http://www.w3.org/2001/XMLSchema-instance" />
              </XmlVisualStateSelector>
            </Selectors>
          </XmlPropertySettingGroup>
          <XmlPropertySettingGroup BasedOn="Padding(10,10,10,-20),Padding(0;2;0;0),IconForeColor">
            <Selectors>
              <XmlVisualStateSelector VisualState="SplitButton">
                <ChildSelector xsi:type="XmlClassSelector" ElementClass="DropDownButtonArrowButton" xmlns:xsi="http://www.w3.org/2001/XMLSchema-instance" />
              </XmlVisualStateSelector>
            </Selectors>
          </XmlPropertySettingGroup>
          <XmlPropertySettingGroup BasedOn="DefaultFont,Padding(4;4;4;4),MainForeColor">
            <Selectors>
              <XmlVisualStateSelector VisualState="SplitButton">
                <ChildSelector xsi:type="XmlTypeSelector" ElementType="Telerik.WinControls.UI.ActionButtonElement" xmlns:xsi="http://www.w3.org/2001/XMLSchema-instance" />
              </XmlVisualStateSelector>
            </Selectors>
          </XmlPropertySettingGroup>
          <XmlPropertySettingGroup BasedOn="">
            <PropertySettings>
              <XmlPropertySetting Property="Telerik.WinControls.RadElement.Visibility" Value="Collapsed" />
            </PropertySettings>
            <Selectors>
              <XmlVisualStateSelector VisualState="SplitButton">
                <ChildSelector xsi:type="XmlClassSelector" ElementClass="RadArrowButtonArrow" xmlns:xsi="http://www.w3.org/2001/XMLSchema-instance" />
              </XmlVisualStateSelector>
            </Selectors>
          </XmlPropertySettingGroup>
          <XmlPropertySettingGroup BasedOn="DefaultFont,MainForeColor">
            <Selectors>
              <XmlVisualStateSelector VisualState="SplitButton" />
            </Selectors>
          </XmlPropertySettingGroup>
          <XmlPropertySettingGroup BasedOn="DisabledForeColor">
            <Selectors>
              <XmlVisualStateSelector VisualState="SplitButton.Disabled" />
            </Selectors>
          </XmlPropertySettingGroup>
          <XmlPropertySettingGroup BasedOn="DisabledForeColor">
            <Selectors>
              <XmlVisualStateSelector VisualState="SplitButton.Disabled">
                <ChildSelector xsi:type="XmlTypeSelector" ElementType="Telerik.WinControls.UI.ActionButtonElement" xmlns:xsi="http://www.w3.org/2001/XMLSchema-instance" />
              </XmlVisualStateSelector>
            </Selectors>
          </XmlPropertySettingGroup>
          <XmlPropertySettingGroup BasedOn="MainBorder">
            <Selectors>
              <XmlVisualStateSelector VisualState="SplitButton">
                <ChildSelector xsi:type="XmlClassSelector" ElementClass="DropDownButtonBorder" xmlns:xsi="http://www.w3.org/2001/XMLSchema-instance" />
              </XmlVisualStateSelector>
            </Selectors>
          </XmlPropertySettingGroup>
          <XmlPropertySettingGroup BasedOn="AccentBorder">
            <Selectors>
              <XmlVisualStateSelector VisualState="SplitButton.Pressed">
                <ChildSelector xsi:type="XmlClassSelector" ElementClass="DropDownButtonBorder" xmlns:xsi="http://www.w3.org/2001/XMLSchema-instance" />
              </XmlVisualStateSelector>
            </Selectors>
          </XmlPropertySettingGroup>
          <XmlPropertySettingGroup BasedOn="AccentBorder">
            <Selectors>
              <XmlVisualStateSelector VisualState="SplitButton.DropDownOpened">
                <ChildSelector xsi:type="XmlClassSelector" ElementClass="DropDownButtonBorder" xmlns:xsi="http://www.w3.org/2001/XMLSchema-instance" />
              </XmlVisualStateSelector>
            </Selectors>
          </XmlPropertySettingGroup>
          <XmlPropertySettingGroup BasedOn="DisabledBorder">
            <Selectors>
              <XmlVisualStateSelector VisualState="SplitButton.Disabled">
                <ChildSelector xsi:type="XmlClassSelector" ElementClass="DropDownButtonBorder" xmlns:xsi="http://www.w3.org/2001/XMLSchema-instance" />
              </XmlVisualStateSelector>
            </Selectors>
          </XmlPropertySettingGroup>
          <XmlPropertySettingGroup BasedOn="MinSize(1;0),ButtonBackgroundFill,MaxSize(1;0)">
            <PropertySettings>
              <XmlPropertySetting Property="Telerik.WinControls.UI.LightVisualElement.DrawBorder" Value="True" />
            </PropertySettings>
            <Selectors>
              <XmlVisualStateSelector VisualState="SplitButton">
                <ChildSelector xsi:type="XmlTypeSelector" ElementType="Telerik.WinControls.UI.LightVisualElement" xmlns:xsi="http://www.w3.org/2001/XMLSchema-instance" />
              </XmlVisualStateSelector>
            </Selectors>
          </XmlPropertySettingGroup>
          <XmlPropertySettingGroup BasedOn="AccentFill">
            <Selectors>
              <XmlVisualStateSelector VisualState="SplitButton.Pressed">
                <ChildSelector xsi:type="XmlTypeSelector" ElementType="Telerik.WinControls.UI.LightVisualElement" xmlns:xsi="http://www.w3.org/2001/XMLSchema-instance" />
              </XmlVisualStateSelector>
            </Selectors>
          </XmlPropertySettingGroup>
          <XmlPropertySettingGroup BasedOn="GlyphText12">
            <PropertySettings>
              <XmlPropertySetting Property="Telerik.WinControls.Primitives.TextPrimitive.Text" Value="" />
            </PropertySettings>
            <Selectors>
              <XmlVisualStateSelector VisualState="SplitButton">
                <ChildSelector xsi:type="XmlClassSelector" ElementClass="RadArrowButtonTextGlyph" xmlns:xsi="http://www.w3.org/2001/XMLSchema-instance" />
              </XmlVisualStateSelector>
            </Selectors>
          </XmlPropertySettingGroup>
          <XmlPropertySettingGroup BasedOn="HighlightedForeColor">
            <Selectors>
              <XmlVisualStateSelector VisualState="SplitButton.MouseOver.ArrowPart">
                <ChildSelector xsi:type="XmlClassSelector" ElementClass="DropDownButtonArrowButton" xmlns:xsi="http://www.w3.org/2001/XMLSchema-instance" />
              </XmlVisualStateSelector>
            </Selectors>
          </XmlPropertySettingGroup>
          <XmlPropertySettingGroup BasedOn="HighlightedForeColor">
            <Selectors>
              <XmlVisualStateSelector VisualState="SplitButton.Pressed">
                <ChildSelector xsi:type="XmlClassSelector" ElementClass="DropDownButtonArrowButton" xmlns:xsi="http://www.w3.org/2001/XMLSchema-instance" />
              </XmlVisualStateSelector>
            </Selectors>
          </XmlPropertySettingGroup>
          <XmlPropertySettingGroup BasedOn="HighlightedForeColor">
            <Selectors>
              <XmlVisualStateSelector VisualState="SplitButton.DropDownOpened">
                <ChildSelector xsi:type="XmlClassSelector" ElementClass="DropDownButtonArrowButton" xmlns:xsi="http://www.w3.org/2001/XMLSchema-instance" />
              </XmlVisualStateSelector>
            </Selectors>
          </XmlPropertySettingGroup>
          <XmlPropertySettingGroup BasedOn="IconForeColor">
            <Selectors>
              <XmlVisualStateSelector VisualState="SplitButton.MouseOver.ActionPart">
                <ChildSelector xsi:type="XmlClassSelector" ElementClass="DropDownButtonArrowButton" xmlns:xsi="http://www.w3.org/2001/XMLSchema-instance" />
              </XmlVisualStateSelector>
            </Selectors>
          </XmlPropertySettingGroup>
          <XmlPropertySettingGroup BasedOn="MainForeColor">
            <Selectors>
              <XmlVisualStateSelector VisualState="SplitButton.MouseOver.ArrowPart">
                <ChildSelector xsi:type="XmlTypeSelector" ElementType="Telerik.WinControls.UI.ActionButtonElement" xmlns:xsi="http://www.w3.org/2001/XMLSchema-instance" />
              </XmlVisualStateSelector>
            </Selectors>
          </XmlPropertySettingGroup>
          <XmlPropertySettingGroup BasedOn="HighlightedForeColor">
            <Selectors>
              <XmlVisualStateSelector VisualState="SplitButton.MouseOver.ActionPart">
                <ChildSelector xsi:type="XmlTypeSelector" ElementType="Telerik.WinControls.UI.ActionButtonElement" xmlns:xsi="http://www.w3.org/2001/XMLSchema-instance" />
              </XmlVisualStateSelector>
            </Selectors>
          </XmlPropertySettingGroup>
          <XmlPropertySettingGroup BasedOn="HighlightedForeColor">
            <Selectors>
              <XmlVisualStateSelector VisualState="SplitButton.Pressed">
                <ChildSelector xsi:type="XmlTypeSelector" ElementType="Telerik.WinControls.UI.ActionButtonElement" xmlns:xsi="http://www.w3.org/2001/XMLSchema-instance" />
              </XmlVisualStateSelector>
            </Selectors>
          </XmlPropertySettingGroup>
          <XmlPropertySettingGroup BasedOn="HighlightedForeColor">
            <Selectors>
              <XmlVisualStateSelector VisualState="SplitButton.DropDownOpened">
                <ChildSelector xsi:type="XmlTypeSelector" ElementType="Telerik.WinControls.UI.ActionButtonElement" xmlns:xsi="http://www.w3.org/2001/XMLSchema-instance" />
              </XmlVisualStateSelector>
            </Selectors>
          </XmlPropertySettingGroup>
          <XmlPropertySettingGroup BasedOn="AlternativeFill">
            <Selectors>
              <XmlVisualStateSelector VisualState="SplitButton.Disabled">
                <ChildSelector xsi:type="XmlClassSelector" ElementClass="ButtonFill" xmlns:xsi="http://www.w3.org/2001/XMLSchema-instance" />
              </XmlVisualStateSelector>
            </Selectors>
          </XmlPropertySettingGroup>
          <XmlPropertySettingGroup BasedOn="AlternativeFill">
            <Selectors>
              <XmlVisualStateSelector VisualState="SplitButton.Disabled">
                <ChildSelector xsi:type="XmlClassSelector" ElementClass="RadArrowButtonFill" xmlns:xsi="http://www.w3.org/2001/XMLSchema-instance" />
              </XmlVisualStateSelector>
            </Selectors>
          </XmlPropertySettingGroup>
          <XmlPropertySettingGroup BasedOn="AccentPressedFill">
            <Selectors>
              <XmlVisualStateSelector VisualState="SplitButton.DropDownOpened">
                <ChildSelector xsi:type="XmlClassSelector" ElementClass="RadArrowButtonFill" xmlns:xsi="http://www.w3.org/2001/XMLSchema-instance" />
              </XmlVisualStateSelector>
            </Selectors>
          </XmlPropertySettingGroup>
          <XmlPropertySettingGroup BasedOn="AccentPressedFill">
            <Selectors>
              <XmlVisualStateSelector VisualState="SplitButton.Pressed">
                <ChildSelector xsi:type="XmlClassSelector" ElementClass="RadArrowButtonFill" xmlns:xsi="http://www.w3.org/2001/XMLSchema-instance" />
              </XmlVisualStateSelector>
            </Selectors>
          </XmlPropertySettingGroup>
          <XmlPropertySettingGroup BasedOn="AccentPressedFill">
            <Selectors>
              <XmlVisualStateSelector VisualState="SplitButton.Pressed">
                <ChildSelector xsi:type="XmlClassSelector" ElementClass="ButtonFill" xmlns:xsi="http://www.w3.org/2001/XMLSchema-instance" />
              </XmlVisualStateSelector>
            </Selectors>
          </XmlPropertySettingGroup>
          <XmlPropertySettingGroup BasedOn="AccentPressedFill">
            <Selectors>
              <XmlVisualStateSelector VisualState="SplitButton.DropDownOpened">
                <ChildSelector xsi:type="XmlClassSelector" ElementClass="ButtonFill" xmlns:xsi="http://www.w3.org/2001/XMLSchema-instance" />
              </XmlVisualStateSelector>
            </Selectors>
          </XmlPropertySettingGroup>
          <XmlPropertySettingGroup BasedOn="AccentMouseOverFill">
            <Selectors>
              <XmlVisualStateSelector VisualState="SplitButton.MouseOver.ActionPart">
                <ChildSelector xsi:type="XmlClassSelector" ElementClass="ButtonFill" xmlns:xsi="http://www.w3.org/2001/XMLSchema-instance" />
              </XmlVisualStateSelector>
            </Selectors>
          </XmlPropertySettingGroup>
          <XmlPropertySettingGroup BasedOn="AccentMouseOverFill">
            <Selectors>
              <XmlVisualStateSelector VisualState="SplitButton.MouseOver.ArrowPart">
                <ChildSelector xsi:type="XmlClassSelector" ElementClass="RadArrowButtonFill" xmlns:xsi="http://www.w3.org/2001/XMLSchema-instance" />
              </XmlVisualStateSelector>
            </Selectors>
          </XmlPropertySettingGroup>
          <XmlPropertySettingGroup BasedOn="ButtonBackgroundFill">
            <Selectors>
              <XmlVisualStateSelector VisualState="SplitButton.MouseOver.ActionPart">
                <ChildSelector xsi:type="XmlClassSelector" ElementClass="RadArrowButtonFill" xmlns:xsi="http://www.w3.org/2001/XMLSchema-instance" />
              </XmlVisualStateSelector>
            </Selectors>
          </XmlPropertySettingGroup>
          <XmlPropertySettingGroup BasedOn="ButtonBackgroundFill">
            <Selectors>
              <XmlVisualStateSelector VisualState="SplitButton.MouseOver.ArrowPart">
                <ChildSelector xsi:type="XmlClassSelector" ElementClass="ButtonFill" xmlns:xsi="http://www.w3.org/2001/XMLSchema-instance" />
              </XmlVisualStateSelector>
            </Selectors>
          </XmlPropertySettingGroup>
          <XmlPropertySettingGroup BasedOn="AccentPressedFill">
            <Selectors>
              <XmlVisualStateSelector VisualState="SplitButton.DropDownOpened">
                <ChildSelector xsi:type="XmlTypeSelector" ElementType="Telerik.WinControls.UI.LightVisualElement" xmlns:xsi="http://www.w3.org/2001/XMLSchema-instance" />
              </XmlVisualStateSelector>
            </Selectors>
          </XmlPropertySettingGroup>
          <XmlPropertySettingGroup BasedOn="AccentMouseOverBorderFill">
            <Selectors>
              <XmlVisualStateSelector VisualState="SplitButton.MouseOver.ArrowPart">
                <ChildSelector xsi:type="XmlTypeSelector" ElementType="Telerik.WinControls.UI.LightVisualElement" xmlns:xsi="http://www.w3.org/2001/XMLSchema-instance" />
              </XmlVisualStateSelector>
            </Selectors>
          </XmlPropertySettingGroup>
          <XmlPropertySettingGroup BasedOn="AccentMouseOverBorderFill">
            <Selectors>
              <XmlVisualStateSelector VisualState="SplitButton.MouseOver.ActionPart">
                <ChildSelector xsi:type="XmlTypeSelector" ElementType="Telerik.WinControls.UI.LightVisualElement" xmlns:xsi="http://www.w3.org/2001/XMLSchema-instance" />
              </XmlVisualStateSelector>
            </Selectors>
          </XmlPropertySettingGroup>
          <XmlPropertySettingGroup BasedOn="AccentMouseOverBorder">
            <Selectors>
              <XmlVisualStateSelector VisualState="SplitButton.MouseOver.ArrowPart">
                <ChildSelector xsi:type="XmlClassSelector" ElementClass="DropDownButtonBorder" xmlns:xsi="http://www.w3.org/2001/XMLSchema-instance" />
              </XmlVisualStateSelector>
            </Selectors>
          </XmlPropertySettingGroup>
          <XmlPropertySettingGroup BasedOn="AccentMouseOverBorder">
            <Selectors>
              <XmlVisualStateSelector VisualState="SplitButton.MouseOver.ActionPart">
                <ChildSelector xsi:type="XmlClassSelector" ElementClass="DropDownButtonBorder" xmlns:xsi="http://www.w3.org/2001/XMLSchema-instance" />
              </XmlVisualStateSelector>
            </Selectors>
          </XmlPropertySettingGroup>
          <XmlPropertySettingGroup BasedOn="AlternativeFill">
            <Selectors>
              <XmlVisualStateSelector VisualState="SplitButton.Disabled">
                <ChildSelector xsi:type="XmlTypeSelector" ElementType="Telerik.WinControls.UI.LightVisualElement" xmlns:xsi="http://www.w3.org/2001/XMLSchema-instance" />
              </XmlVisualStateSelector>
            </Selectors>
          </XmlPropertySettingGroup>
          <XmlPropertySettingGroup BasedOn="DisabledForeColor">
            <Selectors>
              <XmlVisualStateSelector VisualState="SplitButton.Disabled">
                <ChildSelector xsi:type="XmlClassSelector" ElementClass="DropDownButtonArrowButton" xmlns:xsi="http://www.w3.org/2001/XMLSchema-instance" />
              </XmlVisualStateSelector>
            </Selectors>
          </XmlPropertySettingGroup>
        </PropertySettingGroups>
      </BuilderData>
      <StylesheetRelations>
        <RadStylesheetRelation ControlType="Telerik.WinControls.UI.RadSplitButton" ElementType="Telerik.WinControls.RootRadElement" />
        <RadStylesheetRelation RegistrationType="ElementTypeDefault" ElementType="Telerik.WinControls.UI.RadSplitButtonElement" />
      </StylesheetRelations>
    </XmlStyleBuilderRegistration>
  </BuilderRegistrations>
</XmlTheme>